tedana/__about__.py
tedana/__init__.py
tedana/_version.py
tedana/bibtex.py
tedana/combine.py
tedana/config.py
tedana/decay.py
tedana/docs.py
tedana/gscontrol.py
tedana/io.py
tedana/stats.py
tedana/utils.py
tedana/decomposition/__init__.py
tedana/decomposition/ica.py
tedana/decomposition/pca.py
tedana/metrics/__init__.py
tedana/metrics/_utils.py
tedana/metrics/collect.py
tedana/metrics/dependence.py
tedana/metrics/external.py
tedana/reporting/__init__.py
tedana/reporting/dynamic_figures.py
tedana/reporting/html_report.py
tedana/reporting/quality_metrics.py
tedana/reporting/static_figures.py
tedana/reporting/data/README.md
tedana/reporting/data/html/__init__.py
tedana/reporting/data/html/report_body_template.html
tedana/reporting/data/html/report_carpet_buttons_template.html
tedana/reporting/data/html/report_head_template.html
tedana/reporting/data/html/report_info_table_template.html
tedana/resources/references.bib
tedana/resources/config/metrics.json
tedana/resources/config/outputs.json
tedana/resources/decision_trees/demo_external_regressors_motion_task_models.json
tedana/resources/decision_trees/demo_external_regressors_single_model.json
tedana/resources/decision_trees/meica.json
tedana/resources/decision_trees/minimal.json
tedana/resources/decision_trees/tedana_orig.json
tedana/selection/__init__.py
tedana/selection/component_selector.py
tedana/selection/selection_nodes.py
tedana/selection/selection_utils.py
tedana/selection/tedica.py
tedana/selection/tedpca.py
tedana/tests/__init__.py
tedana/tests/conftest.py
tedana/tests/test_bibtex.py
tedana/tests/test_combine.py
tedana/tests/test_component_selector.py
tedana/tests/test_decay.py
tedana/tests/test_external_metrics.py
tedana/tests/test_gscontrol.py
tedana/tests/test_integration.py
tedana/tests/test_io.py
tedana/tests/test_metrics.py
tedana/tests/test_reporting.py
tedana/tests/test_selection_nodes.py
tedana/tests/test_selection_utils.py
tedana/tests/test_stats.py
tedana/tests/test_t2smap.py
tedana-25.1.0.dist-info/METADATA
tedana-25.1.0.dist-info/WHEEL
tedana-25.1.0.dist-info/entry_points.txt
tedana-25.1.0.dist-info/licenses/LICENSE
tedana-25.1.0.dist-info/RECORD
