Metadata-Version: 2.4
Name: tedana
Version: 25.1.0
Summary: TE-Dependent Analysis (tedana) of multi-echo functional magnetic resonance imaging (fMRI) data.
Project-URL: Homepage, https://github.com/ME-ICA/tedana
Project-URL: Documentation, https://www.tedana.readthedocs.io
Project-URL: Paper, https://joss.theoj.org/papers/10.21105/joss.03669
Author: tedana developers
License: GNU LESSER GENERAL PUBLIC LICENSE
License-File: LICENSE
Classifier: Development Status :: 4 - Beta
Classifier: Intended Audience :: Science/Research
Classifier: License :: OSI Approved :: GNU Library or Lesser General Public License (LGPL)
Classifier: Programming Language :: Python :: 3.9
Classifier: Programming Language :: Python :: 3.10
Classifier: Programming Language :: Python :: 3.11
Classifier: Programming Language :: Python :: 3.12
Classifier: Programming Language :: Python :: 3.13
Classifier: Topic :: Scientific/Engineering :: Information Analysis
Requires-Python: >=3.9
Requires-Dist: bokeh<=3.6.3,>=1.0.0
Requires-Dist: mapca<=0.0.5,>=0.0.4
Requires-Dist: matplotlib
Requires-Dist: nibabel<=5.3.2,>=2.5.1
Requires-Dist: nilearn<=0.11.1,>=0.10.3
Requires-Dist: numpy<=2.2.4,>=1.16
Requires-Dist: pandas<=2.3.3,>=2.0
Requires-Dist: pybtex
Requires-Dist: pybtex-apa-style
Requires-Dist: robustica<=0.1.4,>=0.1.4
Requires-Dist: scikit-learn<=1.6.1,>=0.21
Requires-Dist: scipy<=1.15.2,>=1.2.0
Requires-Dist: seaborn<=0.13.2
Requires-Dist: threadpoolctl
Requires-Dist: tqdm
Provides-Extra: all
Requires-Dist: codecov; extra == 'all'
Requires-Dist: coverage; extra == 'all'
Requires-Dist: flake8-absolute-import; extra == 'all'
Requires-Dist: flake8-black; extra == 'all'
Requires-Dist: flake8-docstrings; extra == 'all'
Requires-Dist: flake8-isort; extra == 'all'
Requires-Dist: flake8-pyproject; extra == 'all'
Requires-Dist: flake8-unused-arguments; extra == 'all'
Requires-Dist: flake8-use-fstring; extra == 'all'
Requires-Dist: flake8>=3.7; extra == 'all'
Requires-Dist: pep8-naming; extra == 'all'
Requires-Dist: pre-commit; extra == 'all'
Requires-Dist: pytest; extra == 'all'
Requires-Dist: pytest-cov>=4.0.0; extra == 'all'
Requires-Dist: requests; extra == 'all'
Requires-Dist: sphinx-argparse; extra == 'all'
Requires-Dist: sphinx-copybutton; extra == 'all'
Requires-Dist: sphinx-rtd-theme>=1.2.2; extra == 'all'
Requires-Dist: sphinx>=6.2.1; extra == 'all'
Requires-Dist: sphinxcontrib-bibtex; extra == 'all'
Provides-Extra: dev
Requires-Dist: pre-commit; extra == 'dev'
Provides-Extra: doc
Requires-Dist: sphinx-argparse; extra == 'doc'
Requires-Dist: sphinx-copybutton; extra == 'doc'
Requires-Dist: sphinx-rtd-theme>=1.2.2; extra == 'doc'
Requires-Dist: sphinx>=6.2.1; extra == 'doc'
Requires-Dist: sphinxcontrib-bibtex; extra == 'doc'
Provides-Extra: tests
Requires-Dist: codecov; extra == 'tests'
Requires-Dist: coverage; extra == 'tests'
Requires-Dist: flake8-absolute-import; extra == 'tests'
Requires-Dist: flake8-black; extra == 'tests'
Requires-Dist: flake8-docstrings; extra == 'tests'
Requires-Dist: flake8-isort; extra == 'tests'
Requires-Dist: flake8-pyproject; extra == 'tests'
Requires-Dist: flake8-unused-arguments; extra == 'tests'
Requires-Dist: flake8-use-fstring; extra == 'tests'
Requires-Dist: flake8>=3.7; extra == 'tests'
Requires-Dist: pep8-naming; extra == 'tests'
Requires-Dist: pytest; extra == 'tests'
Requires-Dist: pytest-cov>=4.0.0; extra == 'tests'
Requires-Dist: requests; extra == 'tests'
